{
  "project_info": {
    "project_number": "747241998482",
    "firebase_url": "https://scrum-master-306d1-default-rtdb.europe-west1.firebasedatabase.app",
    "project_id": "scrum-master-306d1",
    "storage_bucket": "scrum-master-306d1.appspot.com"
  },
  "client": [
    {
      "client_info": {
        "mobilesdk_app_id": "1:747241998482:android:30811f99edf981883b7e4b",
        "android_client_info": {
          "package_name": "com.afeka.scrummaster"
        }
      },
      "oauth_client": [
        {
          "client_id": "747241998482-p3a84rc5kd2s95qni9i39suemh0res9q.apps.googleusercontent.com",
          "client_type": 3
        }
      ],
      "api_key": [
        {
          "current_key": "AIzaSyCD9p_YsSupknL93O1UXBK8yn6LT20pPo0"
        }
      ],
      "services": {
        "appinvite_service": {
          "other_platform_oauth_client": [
            {
              "client_id": "747241998482-p3a84rc5kd2s95qni9i39suemh0res9q.apps.googleusercontent.com",
              "client_type": 3
            }
          ]
        }
      }
    }
  ],
  "configuration_version": "1"
}